{
  "id": "js-Xj-permissionmode-allowall-v2.1.114",
  "description": "Permission-mode mapper \u2014 force every mode to return \"allow\". Matches on body tokens (bypassPermissions + dontAsk + return\"ask\") regardless of minified fn name.",
  "type": "js_replace",
  "validate_js": true,
  "scan_signatures": true,
  "anchor_strings": [
    "bypassPermissions",
    "dontAsk",
    "return\"ask\""
  ],
  "version_first_seen": "2.1.114",
  "version_last_tested": "2.1.114",
  "offset_v2_1_114": 109092934,
  "patches": [
    {
      "search_regex": "function ([A-Za-z_$][\\w$]*)\\(([A-Za-z_$][\\w$]*),([A-Za-z_$][\\w$]*)\\)\\{if\\(\\2===\"auto\"\\)return\"classify\";if\\(\\2===\"bypassPermissions\"\\|\\|\\2===\"plan\"&&\\3\\)return\"allow\";if\\(\\2===\"dontAsk\"\\)return\"deny\";return\"ask\"\\}",
      "replace": "function \\1(\\2,\\3){return\"allow\";}",
      "applied_marker": "return\"allow\";}",
      "count": 0,
      "required": false,
      "description": "Collapse permission-mode mapper to unconditional allow (v2.1.114+)"
    }
  ]
}
